package_stat/__init__.py
package_stat/power_stat.py
package_joseph-0.1.0.dist-info/METADATA
package_joseph-0.1.0.dist-info/WHEEL
package_joseph-0.1.0.dist-info/top_level.txt
package_joseph-0.1.0.dist-info/RECORD
