Metadata-Version: 2.2
Name: package_joseph
Version: 0.1.0
Summary: Un package pour calculer la taille nécessaire d’un échantillon pour une étude statistique
Home-page: https://git-scm.pole-emploi.intra/IJBA1200/package-python
Author: Joseph Barreau
Author-email: joseph.barreau@francetravail.fr
Classifier: Programming Language :: Python :: 3
Classifier: License :: OSI Approved :: MIT License
Classifier: Operating System :: OS Independent
Requires-Python: >=3.6
Requires-Dist: scipy
Requires-Dist: numpy
Dynamic: author
Dynamic: author-email
Dynamic: classifier
Dynamic: description
Dynamic: description-content-type
Dynamic: home-page
Dynamic: requires-dist
Dynamic: requires-python
Dynamic: summary
